hi_getter/__init__.py
hi_getter/__main__.py
hi_getter/_version.py
hi_getter/constants.py
hi_getter/events.py
hi_getter/exception_hook.py
hi_getter/lang.py
hi_getter/models.py
hi_getter/py.typed
hi_getter/run.py
hi_getter/tomlfile.py
hi_getter/_vendor/__init__.py
hi_getter/_vendor/packaging/__init__.py
hi_getter/_vendor/packaging/_structures.py
hi_getter/_vendor/packaging/version.py
hi_getter/gui/__init__.py
hi_getter/gui/aliases.py
hi_getter/gui/app.py
hi_getter/gui/workers.py
hi_getter/gui/menus/__init__.py
hi_getter/gui/menus/cache_index.py
hi_getter/gui/menus/column.py
hi_getter/gui/menus/file.py
hi_getter/gui/menus/help.py
hi_getter/gui/menus/tools.py
hi_getter/gui/widgets/__init__.py
hi_getter/gui/widgets/cache_explorer.py
hi_getter/gui/widgets/combo_box.py
hi_getter/gui/widgets/exception_logger.py
hi_getter/gui/widgets/external_text_browser.py
hi_getter/gui/widgets/paste_line_edit.py
hi_getter/gui/windows/__init__.py
hi_getter/gui/windows/application.py
hi_getter/gui/windows/changelog_viewer.py
hi_getter/gui/windows/exception_reporter.py
hi_getter/gui/windows/license_viewer.py
hi_getter/gui/windows/readme_viewer.py
hi_getter/gui/windows/scan_selector_dialog.py
hi_getter/gui/windows/settings.py
hi_getter/network/__init__.py
hi_getter/network/client.py
hi_getter/network/manager.py
hi_getter/network/version_check.py
hi_getter/resources/default_settings.toml
hi_getter/resources/external_icons.json
hi_getter/resources/wp_endpoint_hosts.json
hi_getter/resources/icons/about.png
hi_getter/resources/icons/copyright.png
hi_getter/resources/icons/export.png
hi_getter/resources/icons/folder.png
hi_getter/resources/icons/hi.ico
hi_getter/resources/icons/import.png
hi_getter/resources/icons/settings.png
hi_getter/resources/lang/en.default.json
hi_getter/resources/scripts/CreateShortcut.ps1
hi_getter/resources/scripts/upgrade_version.py
hi_getter/resources/themes/dark/branch_closed.svg
hi_getter/resources/themes/dark/branch_closed_hover.svg
hi_getter-0.13.dist-info/entry_points.txt
hi_getter-0.13.dist-info/LICENSE
hi_getter-0.13.dist-info/WHEEL
hi_getter-0.13.dist-info/METADATA
hi_getter-0.13.dist-info/RECORD
