Metadata-Version: 2.1
Name: hi-getter
Version: 0.13
Summary: A simple way to get live Halo data straight from Halo Waypoint.
Keywords: halo,waypoint,infinite,gui,app,getter,client,unofficial,HaloInfiniteGetter
Author-email: Cubicpath <cubicpath@pm.me>
Requires-Python: >=3.10
Classifier: Development Status :: 3 - Alpha
Classifier: Environment :: X11 Applications :: Qt
Classifier: Intended Audience :: End Users/Desktop
Classifier: License :: OSI Approved :: MIT License
Classifier: Natural Language :: English
Classifier: Operating System :: OS Independent
Classifier: Programming Language :: Python :: 3 :: Only
Classifier: Programming Language :: Python :: 3.10
Classifier: Programming Language :: Python :: 3.11
Classifier: Topic :: Internet :: WWW/HTTP
Classifier: Topic :: Software Development :: User Interfaces
Classifier: Typing :: Typed
Requires-Dist: PySide6_Essentials>=6.4.2
Requires-Dist: toml>=0.10.2
Requires-Dist: py7zr>=0.20.4 ; extra == "all"
Requires-Dist: python-dotenv>=1.0.0 ; extra == "all"
Requires-Dist: autopep8>=2.0.2 ; extra == "dev"
Requires-Dist: bandit>=1.7.4 ; extra == "dev"
Requires-Dist: pydocstyle>=6.3.0 ; extra == "dev"
Requires-Dist: pylint>=2.16.3 ; extra == "dev"
Requires-Dist: pyright>=1.1.296 ; extra == "dev"
Requires-Dist: pyupgrade>=3.3.1 ; extra == "dev"
Project-URL: Issue Tracker, https://github.com/Cubicpath/HaloInfiniteGetter/issues
Project-URL: Source Code, https://github.com/Cubicpath/HaloInfiniteGetter
Provides-Extra: all
Provides-Extra: dev
